sharepoint_graphql/__init__.py
sharepoint_graphql/sharepoint_graphql.py
sharepoint_graphql-0.1.8.dist-info/licenses/LICENSE
sharepoint_graphql-0.1.8.dist-info/METADATA
sharepoint_graphql-0.1.8.dist-info/WHEEL
sharepoint_graphql-0.1.8.dist-info/top_level.txt
sharepoint_graphql-0.1.8.dist-info/RECORD
