Metadata-Version: 2.4
Name: sharepoint_graphql
Version: 0.1.8
Summary: This Python utility enables users to interact with SharePoint sites via Microsoft Graph API, facilitating tasks such as listing, downloading, uploading, moving, and deleting files.
Home-page: https://github.com/woponi/Sharepoint-GraphQL-Python
Author: Pong Wong
Author-email: ninn@opts-db.com
Classifier: Programming Language :: Python :: 3
Classifier: License :: OSI Approved :: MIT License
Classifier: Operating System :: OS Independent
License-File: LICENSE
Requires-Dist: requests
Requires-Dist: msal
Dynamic: author
Dynamic: author-email
Dynamic: classifier
Dynamic: description
Dynamic: description-content-type
Dynamic: home-page
Dynamic: license-file
Dynamic: requires-dist
Dynamic: summary
